truchet_viewer/__init__.py
truchet_viewer/backgrounds.py
truchet_viewer/carlson.py
truchet_viewer/drawing.py
truchet_viewer/helpers.py
truchet_viewer/n6.py
truchet_viewer/smith.py
truchet_viewer/tiler.py
truchet_viewer/truchet.py
truchet_viewer-1.0.0.dist-info/METADATA
truchet_viewer-1.0.0.dist-info/WHEEL
truchet_viewer-1.0.0.dist-info/licenses/LICENSE.txt
truchet_viewer-1.0.0.dist-info/RECORD
