Metadata-Version: 2.4
Name: truchet-viewer
Version: 1.0.0
Summary: A Python library for generating multi-scale Truchet tile patterns and images using PyCairo
Project-URL: Homepage, https://github.com/jobar8/truchet-viewer
Project-URL: Repository, https://github.com/jobar8/truchet-viewer.git
Author: Joseph Barraud
License-Expression: MIT AND (Apache-2.0 OR BSD-2-Clause)
License-File: LICENSE.txt
Keywords: cairo,generative-art,graphics,tiles,truchet
Classifier: Development Status :: 5 - Production/Stable
Classifier: Intended Audience :: Developers
Classifier: Intended Audience :: Science/Research
Classifier: Programming Language :: Python :: 3
Classifier: Programming Language :: Python :: 3.12
Classifier: Programming Language :: Python :: 3.13
Classifier: Programming Language :: Python :: 3.14
Classifier: Topic :: Artistic Software
Classifier: Topic :: Scientific/Engineering :: Image Processing
Requires-Python: >=3.12
Requires-Dist: ipywidgets>=8.1.7
Requires-Dist: jupyterlab>=4.4.3
Requires-Dist: numpy>=1.24.0
Requires-Dist: pillow>=11.2.1
Requires-Dist: pycairo>=1.28.0
Requires-Dist: shapely>=2.1.1
Requires-Dist: streamlit>=1.51.0
Requires-Dist: tqdm>=4.67.1
